fireflyai/__init__.py
fireflyai/api_requestor.py
fireflyai/auth.py
fireflyai/enums.py
fireflyai/errors.py
fireflyai/firefly_response.py
fireflyai/utils.py
fireflyai/version.py
fireflyai/resources/__init__.py
fireflyai/resources/api_resource.py
fireflyai/resources/dataset.py
fireflyai/resources/datasource.py
fireflyai/resources/ensemble.py
fireflyai/resources/prediction.py
fireflyai/resources/task.py
fireflyai-0.0.24.dist-info/DESCRIPTION.rst
fireflyai-0.0.24.dist-info/METADATA
fireflyai-0.0.24.dist-info/RECORD
fireflyai-0.0.24.dist-info/WHEEL
fireflyai-0.0.24.dist-info/metadata.json
fireflyai-0.0.24.dist-info/top_level.txt
